[
    {
        "heart_rate": 159,
        "timestamp": "2024-12-11T11:28:35"
    },
    {
        "heart_rate": 137,
        "timestamp": "2024-12-11T11:28:44.892"
    },
    {
        "heart_rate": 129,
        "timestamp": "2024-12-11T11:28:50"
    },
    {
        "heart_rate": 127,
        "timestamp": "2024-12-11T11:28:56.892"
    },
    {
        "heart_rate": 174,
        "timestamp": "2024-12-11T11:29:09"
    },
    {
        "heart_rate": 121,
        "timestamp": "2024-12-11T11:29:38.892"
    },
    {
        "heart_rate": 152,
        "timestamp": "2024-12-11T11:30:01"
    },
    {
        "heart_rate": 123,
        "timestamp": "2024-12-11T11:30:08.892"
    },
    {
        "heart_rate": 165,
        "timestamp": "2024-12-11T11:30:26"
    },
    {
        "heart_rate": 158,
        "timestamp": "2024-12-11T11:30:51.892"
    },
    {
        "heart_rate": 129,
        "timestamp": "2024-12-11T11:31:04"
    },
    {
        "heart_rate": 154,
        "timestamp": "2024-12-11T11:31:26.892"
    },
    {
        "heart_rate": 163,
        "timestamp": "2024-12-11T11:31:41"
    },
    {
        "heart_rate": 137,
        "timestamp": "2024-12-11T11:32:04.892"
    },
    {
        "heart_rate": 131,
        "timestamp": "2024-12-11T11:32:19"
    },
    {
        "heart_rate": 172,
        "timestamp": "2024-12-11T11:32:34.892"
    },
    {
        "heart_rate": 176,
        "timestamp": "2024-12-11T11:32:50"
    },
    {
        "heart_rate": 180,
        "timestamp": "2024-12-11T11:33:01.892"
    },
    {
        "heart_rate": 180,
        "timestamp": "2024-12-11T11:33:13"
    },
    {
        "heart_rate": 125,
        "timestamp": "2024-12-11T11:33:19.892"
    },
    {
        "heart_rate": 151,
        "timestamp": "2024-12-11T11:33:45"
    },
    {
        "heart_rate": 180,
        "timestamp": "2024-12-11T11:34:12.892"
    },
    {
        "heart_rate": 168,
        "timestamp": "2024-12-11T11:34:28"
    },
    {
        "heart_rate": 122,
        "timestamp": "2024-12-11T11:34:37.892"
    },
    {
        "heart_rate": 153,
        "timestamp": "2024-12-11T11:35:03"
    },
    {
        "heart_rate": 122,
        "timestamp": "2024-12-11T11:35:14.892"
    },
    {
        "heart_rate": 142,
        "timestamp": "2024-12-11T11:35:43"
    },
    {
        "heart_rate": 147,
        "timestamp": "2024-12-11T11:36:01.892"
    },
    {
        "heart_rate": 172,
        "timestamp": "2024-12-11T11:36:30"
    },
    {
        "heart_rate": 131,
        "timestamp": "2024-12-11T11:36:42.892"
    },
    {
        "heart_rate": 174,
        "timestamp": "2024-12-11T11:36:56"
    },
    {
        "heart_rate": 150,
        "timestamp": "2024-12-11T11:37:08.892"
    },
    {
        "heart_rate": 167,
        "timestamp": "2024-12-11T11:37:21"
    },
    {
        "heart_rate": 174,
        "timestamp": "2024-12-11T11:37:45.892"
    },
    {
        "heart_rate": 177,
        "timestamp": "2024-12-11T11:37:54"
    },
    {
        "heart_rate": 127,
        "timestamp": "2024-12-11T11:38:24.892"
    },
    {
        "heart_rate": 174,
        "timestamp": "2024-12-11T11:38:47"
    },
    {
        "heart_rate": 160,
        "timestamp": "2024-12-11T11:39:08.892"
    },
    {
        "heart_rate": 121,
        "timestamp": "2024-12-11T11:39:35"
    },
    {
        "heart_rate": 156,
        "timestamp": "2024-12-11T11:39:59.892"
    },
    {
        "heart_rate": 175,
        "timestamp": "2024-12-11T11:40:25"
    },
    {
        "heart_rate": 142,
        "timestamp": "2024-12-11T11:40:34.892"
    },
    {
        "heart_rate": 171,
        "timestamp": "2024-12-11T11:41:03"
    },
    {
        "heart_rate": 139,
        "timestamp": "2024-12-11T11:41:17.892"
    },
    {
        "heart_rate": 132,
        "timestamp": "2024-12-11T11:41:26"
    },
    {
        "heart_rate": 131,
        "timestamp": "2024-12-11T11:41:45.892"
    },
    {
        "heart_rate": 134,
        "timestamp": "2024-12-11T11:42:05"
    },
    {
        "heart_rate": 130,
        "timestamp": "2024-12-11T11:42:30.892"
    },
    {
        "heart_rate": 131,
        "timestamp": "2024-12-11T11:42:56"
    },
    {
        "heart_rate": 174,
        "timestamp": "2024-12-11T11:43:13.892"
    },
    {
        "heart_rate": 121,
        "timestamp": "2024-12-11T11:43:21"
    },
    {
        "heart_rate": 153,
        "timestamp": "2024-12-11T11:43:37.892"
    },
    {
        "heart_rate": 168,
        "timestamp": "2024-12-11T11:44:05"
    },
    {
        "heart_rate": 162,
        "timestamp": "2024-12-11T11:44:10.892"
    },
    {
        "heart_rate": 179,
        "timestamp": "2024-12-11T11:44:15"
    },
    {
        "heart_rate": 140,
        "timestamp": "2024-12-11T11:44:34.892"
    },
    {
        "heart_rate": 147,
        "timestamp": "2024-12-11T11:44:45"
    },
    {
        "heart_rate": 151,
        "timestamp": "2024-12-11T11:45:05.892"
    },
    {
        "heart_rate": 171,
        "timestamp": "2024-12-11T11:45:35"
    },
    {
        "heart_rate": 123,
        "timestamp": "2024-12-11T11:45:56.892"
    },
    {
        "heart_rate": 174,
        "timestamp": "2024-12-11T11:46:20"
    },
    {
        "heart_rate": 167,
        "timestamp": "2024-12-11T11:46:30.892"
    },
    {
        "heart_rate": 140,
        "timestamp": "2024-12-11T11:46:41"
    },
    {
        "heart_rate": 164,
        "timestamp": "2024-12-11T11:46:59.892"
    },
    {
        "heart_rate": 162,
        "timestamp": "2024-12-11T11:47:26"
    },
    {
        "heart_rate": 156,
        "timestamp": "2024-12-11T11:47:33.892"
    },
    {
        "heart_rate": 137,
        "timestamp": "2024-12-11T11:47:43"
    },
    {
        "heart_rate": 151,
        "timestamp": "2024-12-11T11:48:12.892"
    },
    {
        "heart_rate": 123,
        "timestamp": "2024-12-11T11:48:22"
    },
    {
        "heart_rate": 168,
        "timestamp": "2024-12-11T11:48:49.892"
    },
    {
        "heart_rate": 143,
        "timestamp": "2024-12-11T11:48:58"
    },
    {
        "heart_rate": 156,
        "timestamp": "2024-12-11T11:49:24.892"
    },
    {
        "heart_rate": 123,
        "timestamp": "2024-12-11T11:49:30"
    },
    {
        "heart_rate": 145,
        "timestamp": "2024-12-11T11:49:39.892"
    },
    {
        "heart_rate": 125,
        "timestamp": "2024-12-11T11:50:09"
    },
    {
        "heart_rate": 130,
        "timestamp": "2024-12-11T11:50:29.892"
    },
    {
        "heart_rate": 172,
        "timestamp": "2024-12-11T11:50:47"
    },
    {
        "heart_rate": 141,
        "timestamp": "2024-12-11T11:51:06.892"
    },
    {
        "heart_rate": 144,
        "timestamp": "2024-12-11T11:51:23"
    },
    {
        "heart_rate": 162,
        "timestamp": "2024-12-11T11:51:40.892"
    },
    {
        "heart_rate": 153,
        "timestamp": "2024-12-11T11:52:06"
    },
    {
        "heart_rate": 132,
        "timestamp": "2024-12-11T11:52:11.892"
    },
    {
        "heart_rate": 130,
        "timestamp": "2024-12-11T11:52:28"
    },
    {
        "heart_rate": 166,
        "timestamp": "2024-12-11T11:52:47.892"
    },
    {
        "heart_rate": 141,
        "timestamp": "2024-12-11T11:53:03"
    },
    {
        "heart_rate": 149,
        "timestamp": "2024-12-11T11:53:18.892"
    },
    {
        "heart_rate": 169,
        "timestamp": "2024-12-11T11:53:30"
    },
    {
        "heart_rate": 179,
        "timestamp": "2024-12-11T11:53:52.892"
    },
    {
        "heart_rate": 158,
        "timestamp": "2024-12-11T11:54:15"
    },
    {
        "heart_rate": 125,
        "timestamp": "2024-12-11T11:54:25.892"
    },
    {
        "heart_rate": 125,
        "timestamp": "2024-12-11T11:54:53"
    },
    {
        "heart_rate": 178,
        "timestamp": "2024-12-11T11:55:05.892"
    },
    {
        "heart_rate": 144,
        "timestamp": "2024-12-11T11:55:17"
    },
    {
        "heart_rate": 133,
        "timestamp": "2024-12-11T11:55:31.892"
    },
    {
        "heart_rate": 127,
        "timestamp": "2024-12-11T11:55:45"
    },
    {
        "heart_rate": 159,
        "timestamp": "2024-12-11T11:55:54.892"
    },
    {
        "heart_rate": 143,
        "timestamp": "2024-12-11T11:55:59"
    },
    {
        "heart_rate": 149,
        "timestamp": "2024-12-11T11:56:16.892"
    },
    {
        "heart_rate": 122,
        "timestamp": "2024-12-11T11:56:43"
    },
    {
        "heart_rate": 128,
        "timestamp": "2024-12-11T11:57:09.892"
    },
    {
        "heart_rate": 126,
        "timestamp": "2024-12-11T11:57:37"
    },
    {
        "heart_rate": 121,
        "timestamp": "2024-12-11T11:57:44.892"
    },
    {
        "heart_rate": 172,
        "timestamp": "2024-12-11T11:58:11"
    },
    {
        "heart_rate": 178,
        "timestamp": "2024-12-11T11:58:21.892"
    },
    {
        "heart_rate": 166,
        "timestamp": "2024-12-11T11:58:44"
    },
    {
        "heart_rate": 158,
        "timestamp": "2024-12-11T11:58:49.892"
    },
    {
        "heart_rate": 140,
        "timestamp": "2024-12-11T11:59:16"
    },
    {
        "heart_rate": 137,
        "timestamp": "2024-12-11T11:59:35.892"
    },
    {
        "heart_rate": 159,
        "timestamp": "2024-12-11T11:59:40"
    },
    {
        "heart_rate": 126,
        "timestamp": "2024-12-11T11:59:45.892"
    },
    {
        "heart_rate": 150,
        "timestamp": "2024-12-11T12:00:04"
    },
    {
        "heart_rate": 165,
        "timestamp": "2024-12-11T12:00:22.892"
    },
    {
        "heart_rate": 132,
        "timestamp": "2024-12-11T12:00:42"
    },
    {
        "heart_rate": 158,
        "timestamp": "2024-12-11T12:00:56.892"
    },
    {
        "heart_rate": 167,
        "timestamp": "2024-12-11T12:01:08"
    },
    {
        "heart_rate": 133,
        "timestamp": "2024-12-11T12:01:25.892"
    },
    {
        "heart_rate": 135,
        "timestamp": "2024-12-11T12:01:38"
    },
    {
        "heart_rate": 140,
        "timestamp": "2024-12-11T12:02:05.892"
    },
    {
        "heart_rate": 148,
        "timestamp": "2024-12-11T12:02:17"
    },
    {
        "heart_rate": 145,
        "timestamp": "2024-12-11T12:02:33.892"
    },
    {
        "heart_rate": 162,
        "timestamp": "2024-12-11T12:02:46"
    },
    {
        "heart_rate": 130,
        "timestamp": "2024-12-11T12:03:01.892"
    },
    {
        "heart_rate": 131,
        "timestamp": "2024-12-11T12:03:18"
    },
    {
        "heart_rate": 159,
        "timestamp": "2024-12-11T12:03:45.892"
    },
    {
        "heart_rate": 125,
        "timestamp": "2024-12-11T12:04:13"
    },
    {
        "heart_rate": 157,
        "timestamp": "2024-12-11T12:04:19.892"
    },
    {
        "heart_rate": 179,
        "timestamp": "2024-12-11T12:04:39"
    },
    {
        "heart_rate": 160,
        "timestamp": "2024-12-11T12:05:07.892"
    },
    {
        "heart_rate": 177,
        "timestamp": "2024-12-11T12:05:24"
    },
    {
        "heart_rate": 167,
        "timestamp": "2024-12-11T12:05:44.892"
    },
    {
        "heart_rate": 126,
        "timestamp": "2024-12-11T12:06:05"
    },
    {
        "heart_rate": 167,
        "timestamp": "2024-12-11T12:06:22.892"
    },
    {
        "heart_rate": 125,
        "timestamp": "2024-12-11T12:06:32"
    },
    {
        "heart_rate": 151,
        "timestamp": "2024-12-11T12:07:00.892"
    },
    {
        "heart_rate": 159,
        "timestamp": "2024-12-11T12:07:11"
    },
    {
        "heart_rate": 150,
        "timestamp": "2024-12-11T12:07:37.892"
    },
    {
        "heart_rate": 172,
        "timestamp": "2024-12-11T12:07:54"
    },
    {
        "heart_rate": 172,
        "timestamp": "2024-12-11T12:08:19.892"
    },
    {
        "heart_rate": 138,
        "timestamp": "2024-12-11T12:08:49"
    },
    {
        "heart_rate": 144,
        "timestamp": "2024-12-11T12:09:18.892"
    },
    {
        "heart_rate": 180,
        "timestamp": "2024-12-11T12:09:47"
    },
    {
        "heart_rate": 121,
        "timestamp": "2024-12-11T12:10:07.892"
    },
    {
        "heart_rate": 120,
        "timestamp": "2024-12-11T12:10:23"
    },
    {
        "heart_rate": 164,
        "timestamp": "2024-12-11T12:10:40.892"
    },
    {
        "heart_rate": 170,
        "timestamp": "2024-12-11T12:10:49"
    },
    {
        "heart_rate": 172,
        "timestamp": "2024-12-11T12:10:56.892"
    },
    {
        "heart_rate": 180,
        "timestamp": "2024-12-11T12:11:04"
    },
    {
        "heart_rate": 172,
        "timestamp": "2024-12-11T12:11:28.892"
    },
    {
        "heart_rate": 123,
        "timestamp": "2024-12-11T12:11:49"
    },
    {
        "heart_rate": 120,
        "timestamp": "2024-12-11T12:12:08.892"
    },
    {
        "heart_rate": 163,
        "timestamp": "2024-12-11T12:12:14"
    },
    {
        "heart_rate": 134,
        "timestamp": "2024-12-11T12:12:26.892"
    },
    {
        "heart_rate": 150,
        "timestamp": "2024-12-11T12:12:31"
    },
    {
        "heart_rate": 180,
        "timestamp": "2024-12-11T12:12:38.892"
    },
    {
        "heart_rate": 129,
        "timestamp": "2024-12-11T12:12:53"
    },
    {
        "heart_rate": 165,
        "timestamp": "2024-12-11T12:13:06.892"
    },
    {
        "heart_rate": 126,
        "timestamp": "2024-12-11T12:13:27"
    },
    {
        "heart_rate": 147,
        "timestamp": "2024-12-11T12:13:56.892"
    },
    {
        "heart_rate": 177,
        "timestamp": "2024-12-11T12:14:06"
    },
    {
        "heart_rate": 153,
        "timestamp": "2024-12-11T12:14:19.892"
    },
    {
        "heart_rate": 158,
        "timestamp": "2024-12-11T12:14:31"
    },
    {
        "heart_rate": 141,
        "timestamp": "2024-12-11T12:14:46.892"
    },
    {
        "heart_rate": 122,
        "timestamp": "2024-12-11T12:15:08"
    },
    {
        "heart_rate": 139,
        "timestamp": "2024-12-11T12:15:30.892"
    },
    {
        "heart_rate": 151,
        "timestamp": "2024-12-11T12:15:49"
    },
    {
        "heart_rate": 137,
        "timestamp": "2024-12-11T12:16:01.892"
    },
    {
        "heart_rate": 180,
        "timestamp": "2024-12-11T12:16:15"
    },
    {
        "heart_rate": 164,
        "timestamp": "2024-12-11T12:16:24.892"
    },
    {
        "heart_rate": 130,
        "timestamp": "2024-12-11T12:16:48"
    },
    {
        "heart_rate": 179,
        "timestamp": "2024-12-11T12:17:10.892"
    },
    {
        "heart_rate": 138,
        "timestamp": "2024-12-11T12:17:40"
    },
    {
        "heart_rate": 151,
        "timestamp": "2024-12-11T12:17:59.892"
    },
    {
        "heart_rate": 175,
        "timestamp": "2024-12-11T12:18:05"
    },
    {
        "heart_rate": 163,
        "timestamp": "2024-12-11T12:18:13.892"
    },
    {
        "heart_rate": 158,
        "timestamp": "2024-12-11T12:18:18"
    },
    {
        "heart_rate": 136,
        "timestamp": "2024-12-11T12:18:47.892"
    },
    {
        "heart_rate": 130,
        "timestamp": "2024-12-11T12:19:11"
    },
    {
        "heart_rate": 129,
        "timestamp": "2024-12-11T12:19:16.892"
    },
    {
        "heart_rate": 180,
        "timestamp": "2024-12-11T12:19:26"
    },
    {
        "heart_rate": 133,
        "timestamp": "2024-12-11T12:19:43.892"
    },
    {
        "heart_rate": 132,
        "timestamp": "2024-12-11T12:19:49"
    },
    {
        "heart_rate": 141,
        "timestamp": "2024-12-11T12:20:03.892"
    },
    {
        "heart_rate": 131,
        "timestamp": "2024-12-11T12:20:17"
    },
    {
        "heart_rate": 159,
        "timestamp": "2024-12-11T12:20:27.892"
    },
    {
        "heart_rate": 149,
        "timestamp": "2024-12-11T12:20:49"
    },
    {
        "heart_rate": 164,
        "timestamp": "2024-12-11T12:21:19.892"
    },
    {
        "heart_rate": 159,
        "timestamp": "2024-12-11T12:21:41"
    },
    {
        "heart_rate": 157,
        "timestamp": "2024-12-11T12:21:57.892"
    },
    {
        "heart_rate": 179,
        "timestamp": "2024-12-11T12:22:20"
    },
    {
        "heart_rate": 142,
        "timestamp": "2024-12-11T12:22:28.892"
    },
    {
        "heart_rate": 123,
        "timestamp": "2024-12-11T12:22:40"
    },
    {
        "heart_rate": 169,
        "timestamp": "2024-12-11T12:23:05.892"
    },
    {
        "heart_rate": 172,
        "timestamp": "2024-12-11T12:23:26"
    },
    {
        "heart_rate": 160,
        "timestamp": "2024-12-11T12:23:45.892"
    },
    {
        "heart_rate": 155,
        "timestamp": "2024-12-11T12:24:13"
    },
    {
        "heart_rate": 142,
        "timestamp": "2024-12-11T12:24:23.892"
    },
    {
        "heart_rate": 139,
        "timestamp": "2024-12-11T12:24:38"
    },
    {
        "heart_rate": 158,
        "timestamp": "2024-12-11T12:24:55.892"
    },
    {
        "heart_rate": 136,
        "timestamp": "2024-12-11T12:25:24"
    },
    {
        "heart_rate": 151,
        "timestamp": "2024-12-11T12:25:45.892"
    },
    {
        "heart_rate": 179,
        "timestamp": "2024-12-11T12:26:09"
    },
    {
        "heart_rate": 131,
        "timestamp": "2024-12-11T12:26:21.892"
    },
    {
        "heart_rate": 176,
        "timestamp": "2024-12-11T12:26:50"
    },
    {
        "heart_rate": 149,
        "timestamp": "2024-12-11T12:27:10.892"
    },
    {
        "heart_rate": 121,
        "timestamp": "2024-12-11T12:27:35"
    },
    {
        "heart_rate": 158,
        "timestamp": "2024-12-11T12:28:05.892"
    },
    {
        "heart_rate": 143,
        "timestamp": "2024-12-11T12:28:26"
    },
    {
        "heart_rate": 162,
        "timestamp": "2024-12-11T12:28:37.892"
    },
    {
        "heart_rate": 170,
        "timestamp": "2024-12-11T12:28:59"
    },
    {
        "heart_rate": 155,
        "timestamp": "2024-12-11T12:29:14.892"
    },
    {
        "heart_rate": 120,
        "timestamp": "2024-12-11T12:29:24"
    },
    {
        "heart_rate": 130,
        "timestamp": "2024-12-11T12:29:32.892"
    },
    {
        "heart_rate": 168,
        "timestamp": "2024-12-11T12:29:55"
    },
    {
        "heart_rate": 150,
        "timestamp": "2024-12-11T12:30:19.892"
    },
    {
        "heart_rate": 165,
        "timestamp": "2024-12-11T12:30:37"
    },
    {
        "heart_rate": 146,
        "timestamp": "2024-12-11T12:30:43.892"
    },
    {
        "heart_rate": 144,
        "timestamp": "2024-12-11T12:30:57"
    },
    {
        "heart_rate": 122,
        "timestamp": "2024-12-11T12:31:20.892"
    },
    {
        "heart_rate": 176,
        "timestamp": "2024-12-11T12:31:33"
    },
    {
        "heart_rate": 166,
        "timestamp": "2024-12-11T12:31:52.892"
    },
    {
        "heart_rate": 132,
        "timestamp": "2024-12-11T12:32:07"
    },
    {
        "heart_rate": 122,
        "timestamp": "2024-12-11T12:32:17.892"
    },
    {
        "heart_rate": 173,
        "timestamp": "2024-12-11T12:32:46"
    },
    {
        "heart_rate": 165,
        "timestamp": "2024-12-11T12:32:56.892"
    },
    {
        "heart_rate": 132,
        "timestamp": "2024-12-11T12:33:06"
    },
    {
        "heart_rate": 160,
        "timestamp": "2024-12-11T12:33:35.892"
    },
    {
        "heart_rate": 148,
        "timestamp": "2024-12-11T12:33:50"
    },
    {
        "heart_rate": 157,
        "timestamp": "2024-12-11T12:34:19.892"
    },
    {
        "heart_rate": 144,
        "timestamp": "2024-12-11T12:34:33"
    },
    {
        "heart_rate": 176,
        "timestamp": "2024-12-11T12:35:03.892"
    },
    {
        "heart_rate": 157,
        "timestamp": "2024-12-11T12:35:22"
    },
    {
        "heart_rate": 178,
        "timestamp": "2024-12-11T12:35:32.892"
    },
    {
        "heart_rate": 172,
        "timestamp": "2024-12-11T12:35:55"
    },
    {
        "heart_rate": 167,
        "timestamp": "2024-12-11T12:36:16.892"
    },
    {
        "heart_rate": 146,
        "timestamp": "2024-12-11T12:36:44"
    },
    {
        "heart_rate": 153,
        "timestamp": "2024-12-11T12:36:54.892"
    },
    {
        "heart_rate": 164,
        "timestamp": "2024-12-11T12:37:17"
    },
    {
        "heart_rate": 125,
        "timestamp": "2024-12-11T12:37:32.892"
    },
    {
        "heart_rate": 170,
        "timestamp": "2024-12-11T12:37:48"
    },
    {
        "heart_rate": 147,
        "timestamp": "2024-12-11T12:38:09.892"
    },
    {
        "heart_rate": 163,
        "timestamp": "2024-12-11T12:38:17"
    },
    {
        "heart_rate": 127,
        "timestamp": "2024-12-11T12:38:39.892"
    },
    {
        "heart_rate": 162,
        "timestamp": "2024-12-11T12:38:54"
    },
    {
        "heart_rate": 175,
        "timestamp": "2024-12-11T12:39:02.892"
    },
    {
        "heart_rate": 163,
        "timestamp": "2024-12-11T12:39:11"
    },
    {
        "heart_rate": 157,
        "timestamp": "2024-12-11T12:39:29.892"
    },
    {
        "heart_rate": 137,
        "timestamp": "2024-12-11T12:39:42"
    },
    {
        "heart_rate": 127,
        "timestamp": "2024-12-11T12:39:52.892"
    },
    {
        "heart_rate": 160,
        "timestamp": "2024-12-11T12:40:09"
    },
    {
        "heart_rate": 131,
        "timestamp": "2024-12-11T12:40:14.892"
    },
    {
        "heart_rate": 142,
        "timestamp": "2024-12-11T12:40:25"
    },
    {
        "heart_rate": 147,
        "timestamp": "2024-12-11T12:40:37.892"
    },
    {
        "heart_rate": 157,
        "timestamp": "2024-12-11T12:40:53"
    },
    {
        "heart_rate": 175,
        "timestamp": "2024-12-11T12:41:12.892"
    },
    {
        "heart_rate": 163,
        "timestamp": "2024-12-11T12:41:28"
    },
    {
        "heart_rate": 141,
        "timestamp": "2024-12-11T12:41:34.892"
    },
    {
        "heart_rate": 150,
        "timestamp": "2024-12-11T12:41:47"
    },
    {
        "heart_rate": 146,
        "timestamp": "2024-12-11T12:42:14.892"
    },
    {
        "heart_rate": 125,
        "timestamp": "2024-12-11T12:42:20"
    },
    {
        "heart_rate": 146,
        "timestamp": "2024-12-11T12:42:38.892"
    },
    {
        "heart_rate": 127,
        "timestamp": "2024-12-11T12:43:02"
    },
    {
        "heart_rate": 180,
        "timestamp": "2024-12-11T12:43:10.892"
    },
    {
        "heart_rate": 123,
        "timestamp": "2024-12-11T12:43:22"
    },
    {
        "heart_rate": 156,
        "timestamp": "2024-12-11T12:43:27.892"
    },
    {
        "heart_rate": 144,
        "timestamp": "2024-12-11T12:43:32"
    },
    {
        "heart_rate": 170,
        "timestamp": "2024-12-11T12:43:57.892"
    },
    {
        "heart_rate": 157,
        "timestamp": "2024-12-11T12:44:12"
    },
    {
        "heart_rate": 165,
        "timestamp": "2024-12-11T12:44:31.892"
    },
    {
        "heart_rate": 178,
        "timestamp": "2024-12-11T12:44:53"
    },
    {
        "heart_rate": 161,
        "timestamp": "2024-12-11T12:45:09.892"
    },
    {
        "heart_rate": 130,
        "timestamp": "2024-12-11T12:45:22"
    },
    {
        "heart_rate": 124,
        "timestamp": "2024-12-11T12:45:45.892"
    },
    {
        "heart_rate": 135,
        "timestamp": "2024-12-11T12:45:52"
    },
    {
        "heart_rate": 131,
        "timestamp": "2024-12-11T12:46:21.892"
    },
    {
        "heart_rate": 163,
        "timestamp": "2024-12-11T12:46:45"
    },
    {
        "heart_rate": 136,
        "timestamp": "2024-12-11T12:47:10.892"
    },
    {
        "heart_rate": 154,
        "timestamp": "2024-12-11T12:47:21"
    },
    {
        "heart_rate": 165,
        "timestamp": "2024-12-11T12:47:41.892"
    },
    {
        "heart_rate": 133,
        "timestamp": "2024-12-11T12:48:01"
    },
    {
        "heart_rate": 159,
        "timestamp": "2024-12-11T12:48:25.892"
    },
    {
        "heart_rate": 122,
        "timestamp": "2024-12-11T12:48:33"
    },
    {
        "heart_rate": 121,
        "timestamp": "2024-12-11T12:48:42.892"
    },
    {
        "heart_rate": 138,
        "timestamp": "2024-12-11T12:48:54"
    },
    {
        "heart_rate": 168,
        "timestamp": "2024-12-11T12:49:00.892"
    },
    {
        "heart_rate": 151,
        "timestamp": "2024-12-11T12:49:10"
    },
    {
        "heart_rate": 152,
        "timestamp": "2024-12-11T12:49:25.892"
    },
    {
        "heart_rate": 170,
        "timestamp": "2024-12-11T12:49:54"
    },
    {
        "heart_rate": 123,
        "timestamp": "2024-12-11T12:50:18.892"
    },
    {
        "heart_rate": 175,
        "timestamp": "2024-12-11T12:50:38"
    },
    {
        "heart_rate": 163,
        "timestamp": "2024-12-11T12:50:45.892"
    },
    {
        "heart_rate": 128,
        "timestamp": "2024-12-11T12:51:07"
    }
]