[
    {
        "heart_rate": 172,
        "timestamp": "2024-12-11T11:28:36"
    },
    {
        "heart_rate": 172,
        "timestamp": "2024-12-11T11:28:43.267"
    },
    {
        "heart_rate": 171,
        "timestamp": "2024-12-11T11:29:09"
    },
    {
        "heart_rate": 124,
        "timestamp": "2024-12-11T11:29:32.267"
    },
    {
        "heart_rate": 123,
        "timestamp": "2024-12-11T11:29:52"
    },
    {
        "heart_rate": 123,
        "timestamp": "2024-12-11T11:29:57.267"
    },
    {
        "heart_rate": 140,
        "timestamp": "2024-12-11T11:30:07"
    },
    {
        "heart_rate": 166,
        "timestamp": "2024-12-11T11:30:30.267"
    },
    {
        "heart_rate": 157,
        "timestamp": "2024-12-11T11:30:42"
    },
    {
        "heart_rate": 142,
        "timestamp": "2024-12-11T11:30:58.267"
    },
    {
        "heart_rate": 148,
        "timestamp": "2024-12-11T11:31:24"
    },
    {
        "heart_rate": 167,
        "timestamp": "2024-12-11T11:31:49.267"
    },
    {
        "heart_rate": 120,
        "timestamp": "2024-12-11T11:32:11"
    },
    {
        "heart_rate": 172,
        "timestamp": "2024-12-11T11:32:23.267"
    },
    {
        "heart_rate": 154,
        "timestamp": "2024-12-11T11:32:44"
    },
    {
        "heart_rate": 136,
        "timestamp": "2024-12-11T11:33:04.267"
    },
    {
        "heart_rate": 121,
        "timestamp": "2024-12-11T11:33:27"
    },
    {
        "heart_rate": 133,
        "timestamp": "2024-12-11T11:33:57.267"
    },
    {
        "heart_rate": 132,
        "timestamp": "2024-12-11T11:34:06"
    },
    {
        "heart_rate": 142,
        "timestamp": "2024-12-11T11:34:13.267"
    },
    {
        "heart_rate": 143,
        "timestamp": "2024-12-11T11:34:35"
    },
    {
        "heart_rate": 122,
        "timestamp": "2024-12-11T11:35:04.267"
    },
    {
        "heart_rate": 151,
        "timestamp": "2024-12-11T11:35:11"
    },
    {
        "heart_rate": 149,
        "timestamp": "2024-12-11T11:35:23.267"
    },
    {
        "heart_rate": 147,
        "timestamp": "2024-12-11T11:35:40"
    },
    {
        "heart_rate": 150,
        "timestamp": "2024-12-11T11:36:07.267"
    },
    {
        "heart_rate": 169,
        "timestamp": "2024-12-11T11:36:29"
    },
    {
        "heart_rate": 133,
        "timestamp": "2024-12-11T11:36:58.267"
    },
    {
        "heart_rate": 170,
        "timestamp": "2024-12-11T11:37:15"
    },
    {
        "heart_rate": 178,
        "timestamp": "2024-12-11T11:37:27.267"
    },
    {
        "heart_rate": 169,
        "timestamp": "2024-12-11T11:37:39"
    },
    {
        "heart_rate": 143,
        "timestamp": "2024-12-11T11:38:00.267"
    },
    {
        "heart_rate": 175,
        "timestamp": "2024-12-11T11:38:18"
    },
    {
        "heart_rate": 154,
        "timestamp": "2024-12-11T11:38:36.267"
    },
    {
        "heart_rate": 179,
        "timestamp": "2024-12-11T11:38:49"
    },
    {
        "heart_rate": 169,
        "timestamp": "2024-12-11T11:39:17.267"
    },
    {
        "heart_rate": 160,
        "timestamp": "2024-12-11T11:39:23"
    },
    {
        "heart_rate": 124,
        "timestamp": "2024-12-11T11:39:35.267"
    },
    {
        "heart_rate": 172,
        "timestamp": "2024-12-11T11:40:00"
    },
    {
        "heart_rate": 138,
        "timestamp": "2024-12-11T11:40:22.267"
    },
    {
        "heart_rate": 160,
        "timestamp": "2024-12-11T11:40:48"
    },
    {
        "heart_rate": 163,
        "timestamp": "2024-12-11T11:40:56.267"
    },
    {
        "heart_rate": 159,
        "timestamp": "2024-12-11T11:41:15"
    },
    {
        "heart_rate": 169,
        "timestamp": "2024-12-11T11:41:28.267"
    },
    {
        "heart_rate": 120,
        "timestamp": "2024-12-11T11:41:36"
    },
    {
        "heart_rate": 143,
        "timestamp": "2024-12-11T11:41:56.267"
    },
    {
        "heart_rate": 144,
        "timestamp": "2024-12-11T11:42:08"
    },
    {
        "heart_rate": 133,
        "timestamp": "2024-12-11T11:42:36.267"
    },
    {
        "heart_rate": 175,
        "timestamp": "2024-12-11T11:42:43"
    },
    {
        "heart_rate": 128,
        "timestamp": "2024-12-11T11:42:49.267"
    },
    {
        "heart_rate": 140,
        "timestamp": "2024-12-11T11:43:19"
    },
    {
        "heart_rate": 168,
        "timestamp": "2024-12-11T11:43:24.267"
    },
    {
        "heart_rate": 138,
        "timestamp": "2024-12-11T11:43:45"
    },
    {
        "heart_rate": 158,
        "timestamp": "2024-12-11T11:43:54.267"
    },
    {
        "heart_rate": 135,
        "timestamp": "2024-12-11T11:44:06"
    },
    {
        "heart_rate": 154,
        "timestamp": "2024-12-11T11:44:14.267"
    },
    {
        "heart_rate": 130,
        "timestamp": "2024-12-11T11:44:25"
    },
    {
        "heart_rate": 166,
        "timestamp": "2024-12-11T11:44:51.267"
    },
    {
        "heart_rate": 122,
        "timestamp": "2024-12-11T11:45:03"
    },
    {
        "heart_rate": 173,
        "timestamp": "2024-12-11T11:45:31.267"
    },
    {
        "heart_rate": 180,
        "timestamp": "2024-12-11T11:45:40"
    },
    {
        "heart_rate": 163,
        "timestamp": "2024-12-11T11:45:54.267"
    },
    {
        "heart_rate": 166,
        "timestamp": "2024-12-11T11:46:04"
    },
    {
        "heart_rate": 160,
        "timestamp": "2024-12-11T11:46:13.267"
    },
    {
        "heart_rate": 130,
        "timestamp": "2024-12-11T11:46:23"
    },
    {
        "heart_rate": 156,
        "timestamp": "2024-12-11T11:46:37.267"
    },
    {
        "heart_rate": 161,
        "timestamp": "2024-12-11T11:46:49"
    },
    {
        "heart_rate": 139,
        "timestamp": "2024-12-11T11:47:18.267"
    },
    {
        "heart_rate": 144,
        "timestamp": "2024-12-11T11:47:40"
    },
    {
        "heart_rate": 134,
        "timestamp": "2024-12-11T11:48:05.267"
    },
    {
        "heart_rate": 161,
        "timestamp": "2024-12-11T11:48:29"
    },
    {
        "heart_rate": 180,
        "timestamp": "2024-12-11T11:48:38.267"
    },
    {
        "heart_rate": 177,
        "timestamp": "2024-12-11T11:49:05"
    },
    {
        "heart_rate": 178,
        "timestamp": "2024-12-11T11:49:20.267"
    },
    {
        "heart_rate": 164,
        "timestamp": "2024-12-11T11:49:29"
    },
    {
        "heart_rate": 167,
        "timestamp": "2024-12-11T11:49:44.267"
    },
    {
        "heart_rate": 122,
        "timestamp": "2024-12-11T11:50:08"
    },
    {
        "heart_rate": 157,
        "timestamp": "2024-12-11T11:50:28.267"
    },
    {
        "heart_rate": 157,
        "timestamp": "2024-12-11T11:50:47"
    },
    {
        "heart_rate": 135,
        "timestamp": "2024-12-11T11:51:13.267"
    },
    {
        "heart_rate": 130,
        "timestamp": "2024-12-11T11:51:39"
    },
    {
        "heart_rate": 178,
        "timestamp": "2024-12-11T11:51:54.267"
    },
    {
        "heart_rate": 121,
        "timestamp": "2024-12-11T11:52:21"
    },
    {
        "heart_rate": 144,
        "timestamp": "2024-12-11T11:52:37.267"
    },
    {
        "heart_rate": 164,
        "timestamp": "2024-12-11T11:52:56"
    },
    {
        "heart_rate": 161,
        "timestamp": "2024-12-11T11:53:12.267"
    },
    {
        "heart_rate": 126,
        "timestamp": "2024-12-11T11:53:28"
    },
    {
        "heart_rate": 156,
        "timestamp": "2024-12-11T11:53:51.267"
    },
    {
        "heart_rate": 136,
        "timestamp": "2024-12-11T11:54:06"
    },
    {
        "heart_rate": 158,
        "timestamp": "2024-12-11T11:54:12.267"
    },
    {
        "heart_rate": 140,
        "timestamp": "2024-12-11T11:54:42"
    },
    {
        "heart_rate": 129,
        "timestamp": "2024-12-11T11:55:01.267"
    },
    {
        "heart_rate": 137,
        "timestamp": "2024-12-11T11:55:13"
    },
    {
        "heart_rate": 155,
        "timestamp": "2024-12-11T11:55:31.267"
    },
    {
        "heart_rate": 123,
        "timestamp": "2024-12-11T11:55:56"
    },
    {
        "heart_rate": 156,
        "timestamp": "2024-12-11T11:56:12.267"
    },
    {
        "heart_rate": 137,
        "timestamp": "2024-12-11T11:56:24"
    },
    {
        "heart_rate": 155,
        "timestamp": "2024-12-11T11:56:46.267"
    },
    {
        "heart_rate": 166,
        "timestamp": "2024-12-11T11:57:01"
    },
    {
        "heart_rate": 168,
        "timestamp": "2024-12-11T11:57:29.267"
    },
    {
        "heart_rate": 127,
        "timestamp": "2024-12-11T11:57:39"
    },
    {
        "heart_rate": 159,
        "timestamp": "2024-12-11T11:57:47.267"
    },
    {
        "heart_rate": 141,
        "timestamp": "2024-12-11T11:58:06"
    },
    {
        "heart_rate": 154,
        "timestamp": "2024-12-11T11:58:19.267"
    },
    {
        "heart_rate": 141,
        "timestamp": "2024-12-11T11:58:49"
    },
    {
        "heart_rate": 179,
        "timestamp": "2024-12-11T11:59:19.267"
    },
    {
        "heart_rate": 163,
        "timestamp": "2024-12-11T11:59:36"
    },
    {
        "heart_rate": 159,
        "timestamp": "2024-12-11T11:59:56.267"
    },
    {
        "heart_rate": 161,
        "timestamp": "2024-12-11T12:00:18"
    },
    {
        "heart_rate": 179,
        "timestamp": "2024-12-11T12:00:44.267"
    },
    {
        "heart_rate": 135,
        "timestamp": "2024-12-11T12:01:08"
    },
    {
        "heart_rate": 123,
        "timestamp": "2024-12-11T12:01:15.267"
    },
    {
        "heart_rate": 166,
        "timestamp": "2024-12-11T12:01:41"
    },
    {
        "heart_rate": 178,
        "timestamp": "2024-12-11T12:02:09.267"
    },
    {
        "heart_rate": 150,
        "timestamp": "2024-12-11T12:02:30"
    },
    {
        "heart_rate": 171,
        "timestamp": "2024-12-11T12:02:40.267"
    },
    {
        "heart_rate": 161,
        "timestamp": "2024-12-11T12:03:03"
    },
    {
        "heart_rate": 177,
        "timestamp": "2024-12-11T12:03:26.267"
    },
    {
        "heart_rate": 169,
        "timestamp": "2024-12-11T12:03:38"
    },
    {
        "heart_rate": 159,
        "timestamp": "2024-12-11T12:04:07.267"
    },
    {
        "heart_rate": 133,
        "timestamp": "2024-12-11T12:04:33"
    },
    {
        "heart_rate": 179,
        "timestamp": "2024-12-11T12:04:42.267"
    },
    {
        "heart_rate": 130,
        "timestamp": "2024-12-11T12:05:10"
    },
    {
        "heart_rate": 131,
        "timestamp": "2024-12-11T12:05:26.267"
    },
    {
        "heart_rate": 162,
        "timestamp": "2024-12-11T12:05:54"
    },
    {
        "heart_rate": 139,
        "timestamp": "2024-12-11T12:06:18.267"
    },
    {
        "heart_rate": 139,
        "timestamp": "2024-12-11T12:06:39"
    },
    {
        "heart_rate": 142,
        "timestamp": "2024-12-11T12:06:46.267"
    },
    {
        "heart_rate": 126,
        "timestamp": "2024-12-11T12:07:07"
    },
    {
        "heart_rate": 136,
        "timestamp": "2024-12-11T12:07:18.267"
    },
    {
        "heart_rate": 154,
        "timestamp": "2024-12-11T12:07:46"
    },
    {
        "heart_rate": 164,
        "timestamp": "2024-12-11T12:08:10.267"
    },
    {
        "heart_rate": 147,
        "timestamp": "2024-12-11T12:08:26"
    },
    {
        "heart_rate": 137,
        "timestamp": "2024-12-11T12:08:34.267"
    },
    {
        "heart_rate": 163,
        "timestamp": "2024-12-11T12:08:39"
    },
    {
        "heart_rate": 128,
        "timestamp": "2024-12-11T12:08:56.267"
    },
    {
        "heart_rate": 175,
        "timestamp": "2024-12-11T12:09:06"
    },
    {
        "heart_rate": 128,
        "timestamp": "2024-12-11T12:09:30.267"
    },
    {
        "heart_rate": 153,
        "timestamp": "2024-12-11T12:09:58"
    },
    {
        "heart_rate": 168,
        "timestamp": "2024-12-11T12:10:27.267"
    },
    {
        "heart_rate": 135,
        "timestamp": "2024-12-11T12:10:57"
    },
    {
        "heart_rate": 148,
        "timestamp": "2024-12-11T12:11:07.267"
    },
    {
        "heart_rate": 160,
        "timestamp": "2024-12-11T12:11:27"
    },
    {
        "heart_rate": 147,
        "timestamp": "2024-12-11T12:11:39.267"
    },
    {
        "heart_rate": 143,
        "timestamp": "2024-12-11T12:12:06"
    },
    {
        "heart_rate": 142,
        "timestamp": "2024-12-11T12:12:22.267"
    },
    {
        "heart_rate": 123,
        "timestamp": "2024-12-11T12:12:52"
    },
    {
        "heart_rate": 126,
        "timestamp": "2024-12-11T12:13:11.267"
    },
    {
        "heart_rate": 146,
        "timestamp": "2024-12-11T12:13:40"
    },
    {
        "heart_rate": 161,
        "timestamp": "2024-12-11T12:14:02.267"
    },
    {
        "heart_rate": 127,
        "timestamp": "2024-12-11T12:14:31"
    },
    {
        "heart_rate": 126,
        "timestamp": "2024-12-11T12:14:39.267"
    },
    {
        "heart_rate": 175,
        "timestamp": "2024-12-11T12:14:50"
    },
    {
        "heart_rate": 176,
        "timestamp": "2024-12-11T12:15:04.267"
    },
    {
        "heart_rate": 179,
        "timestamp": "2024-12-11T12:15:12"
    },
    {
        "heart_rate": 172,
        "timestamp": "2024-12-11T12:15:20.267"
    },
    {
        "heart_rate": 130,
        "timestamp": "2024-12-11T12:15:39"
    },
    {
        "heart_rate": 152,
        "timestamp": "2024-12-11T12:16:03.267"
    },
    {
        "heart_rate": 164,
        "timestamp": "2024-12-11T12:16:28"
    },
    {
        "heart_rate": 163,
        "timestamp": "2024-12-11T12:16:53.267"
    },
    {
        "heart_rate": 176,
        "timestamp": "2024-12-11T12:17:02"
    },
    {
        "heart_rate": 124,
        "timestamp": "2024-12-11T12:17:24.267"
    },
    {
        "heart_rate": 148,
        "timestamp": "2024-12-11T12:17:29"
    },
    {
        "heart_rate": 130,
        "timestamp": "2024-12-11T12:17:36.267"
    },
    {
        "heart_rate": 158,
        "timestamp": "2024-12-11T12:18:02"
    },
    {
        "heart_rate": 166,
        "timestamp": "2024-12-11T12:18:22.267"
    },
    {
        "heart_rate": 148,
        "timestamp": "2024-12-11T12:18:49"
    },
    {
        "heart_rate": 160,
        "timestamp": "2024-12-11T12:18:54.267"
    },
    {
        "heart_rate": 175,
        "timestamp": "2024-12-11T12:19:20"
    },
    {
        "heart_rate": 154,
        "timestamp": "2024-12-11T12:19:40.267"
    },
    {
        "heart_rate": 179,
        "timestamp": "2024-12-11T12:20:04"
    },
    {
        "heart_rate": 170,
        "timestamp": "2024-12-11T12:20:33.267"
    },
    {
        "heart_rate": 169,
        "timestamp": "2024-12-11T12:20:38"
    },
    {
        "heart_rate": 152,
        "timestamp": "2024-12-11T12:21:03.267"
    },
    {
        "heart_rate": 156,
        "timestamp": "2024-12-11T12:21:17"
    },
    {
        "heart_rate": 169,
        "timestamp": "2024-12-11T12:21:42.267"
    },
    {
        "heart_rate": 166,
        "timestamp": "2024-12-11T12:22:02"
    },
    {
        "heart_rate": 177,
        "timestamp": "2024-12-11T12:22:26.267"
    },
    {
        "heart_rate": 140,
        "timestamp": "2024-12-11T12:22:33"
    },
    {
        "heart_rate": 175,
        "timestamp": "2024-12-11T12:22:46.267"
    },
    {
        "heart_rate": 165,
        "timestamp": "2024-12-11T12:22:55"
    },
    {
        "heart_rate": 160,
        "timestamp": "2024-12-11T12:23:16.267"
    },
    {
        "heart_rate": 140,
        "timestamp": "2024-12-11T12:23:21"
    },
    {
        "heart_rate": 158,
        "timestamp": "2024-12-11T12:23:28.267"
    },
    {
        "heart_rate": 140,
        "timestamp": "2024-12-11T12:23:33"
    },
    {
        "heart_rate": 127,
        "timestamp": "2024-12-11T12:23:48.267"
    },
    {
        "heart_rate": 136,
        "timestamp": "2024-12-11T12:24:01"
    },
    {
        "heart_rate": 165,
        "timestamp": "2024-12-11T12:24:09.267"
    },
    {
        "heart_rate": 175,
        "timestamp": "2024-12-11T12:24:25"
    },
    {
        "heart_rate": 138,
        "timestamp": "2024-12-11T12:24:51.267"
    },
    {
        "heart_rate": 166,
        "timestamp": "2024-12-11T12:25:01"
    },
    {
        "heart_rate": 130,
        "timestamp": "2024-12-11T12:25:19.267"
    },
    {
        "heart_rate": 156,
        "timestamp": "2024-12-11T12:25:26"
    },
    {
        "heart_rate": 150,
        "timestamp": "2024-12-11T12:25:47.267"
    },
    {
        "heart_rate": 159,
        "timestamp": "2024-12-11T12:25:59"
    },
    {
        "heart_rate": 154,
        "timestamp": "2024-12-11T12:26:19.267"
    },
    {
        "heart_rate": 157,
        "timestamp": "2024-12-11T12:26:37"
    },
    {
        "heart_rate": 165,
        "timestamp": "2024-12-11T12:27:05.267"
    },
    {
        "heart_rate": 121,
        "timestamp": "2024-12-11T12:27:21"
    },
    {
        "heart_rate": 174,
        "timestamp": "2024-12-11T12:27:31.267"
    },
    {
        "heart_rate": 152,
        "timestamp": "2024-12-11T12:27:58"
    },
    {
        "heart_rate": 141,
        "timestamp": "2024-12-11T12:28:06.267"
    },
    {
        "heart_rate": 130,
        "timestamp": "2024-12-11T12:28:27"
    },
    {
        "heart_rate": 156,
        "timestamp": "2024-12-11T12:28:43.267"
    },
    {
        "heart_rate": 136,
        "timestamp": "2024-12-11T12:29:05"
    },
    {
        "heart_rate": 140,
        "timestamp": "2024-12-11T12:29:17.267"
    },
    {
        "heart_rate": 124,
        "timestamp": "2024-12-11T12:29:40"
    },
    {
        "heart_rate": 156,
        "timestamp": "2024-12-11T12:29:52.267"
    },
    {
        "heart_rate": 141,
        "timestamp": "2024-12-11T12:29:59"
    },
    {
        "heart_rate": 126,
        "timestamp": "2024-12-11T12:30:25.267"
    },
    {
        "heart_rate": 165,
        "timestamp": "2024-12-11T12:30:32"
    },
    {
        "heart_rate": 142,
        "timestamp": "2024-12-11T12:30:49.267"
    },
    {
        "heart_rate": 177,
        "timestamp": "2024-12-11T12:31:19"
    },
    {
        "heart_rate": 156,
        "timestamp": "2024-12-11T12:31:38.267"
    },
    {
        "heart_rate": 122,
        "timestamp": "2024-12-11T12:32:02"
    },
    {
        "heart_rate": 132,
        "timestamp": "2024-12-11T12:32:18.267"
    },
    {
        "heart_rate": 177,
        "timestamp": "2024-12-11T12:32:39"
    },
    {
        "heart_rate": 141,
        "timestamp": "2024-12-11T12:32:56.267"
    },
    {
        "heart_rate": 156,
        "timestamp": "2024-12-11T12:33:06"
    },
    {
        "heart_rate": 166,
        "timestamp": "2024-12-11T12:33:12.267"
    },
    {
        "heart_rate": 125,
        "timestamp": "2024-12-11T12:33:26"
    },
    {
        "heart_rate": 168,
        "timestamp": "2024-12-11T12:33:45.267"
    },
    {
        "heart_rate": 180,
        "timestamp": "2024-12-11T12:34:04"
    },
    {
        "heart_rate": 171,
        "timestamp": "2024-12-11T12:34:22.267"
    },
    {
        "heart_rate": 139,
        "timestamp": "2024-12-11T12:34:39"
    },
    {
        "heart_rate": 134,
        "timestamp": "2024-12-11T12:34:47.267"
    },
    {
        "heart_rate": 122,
        "timestamp": "2024-12-11T12:35:11"
    },
    {
        "heart_rate": 179,
        "timestamp": "2024-12-11T12:35:25.267"
    },
    {
        "heart_rate": 146,
        "timestamp": "2024-12-11T12:35:33"
    },
    {
        "heart_rate": 135,
        "timestamp": "2024-12-11T12:36:01.267"
    },
    {
        "heart_rate": 164,
        "timestamp": "2024-12-11T12:36:28"
    },
    {
        "heart_rate": 179,
        "timestamp": "2024-12-11T12:36:51.267"
    },
    {
        "heart_rate": 133,
        "timestamp": "2024-12-11T12:37:17"
    },
    {
        "heart_rate": 164,
        "timestamp": "2024-12-11T12:37:30.267"
    },
    {
        "heart_rate": 169,
        "timestamp": "2024-12-11T12:37:50"
    },
    {
        "heart_rate": 141,
        "timestamp": "2024-12-11T12:38:14.267"
    },
    {
        "heart_rate": 124,
        "timestamp": "2024-12-11T12:38:25"
    },
    {
        "heart_rate": 137,
        "timestamp": "2024-12-11T12:38:30.267"
    },
    {
        "heart_rate": 122,
        "timestamp": "2024-12-11T12:38:52"
    },
    {
        "heart_rate": 177,
        "timestamp": "2024-12-11T12:39:11.267"
    },
    {
        "heart_rate": 130,
        "timestamp": "2024-12-11T12:39:38"
    },
    {
        "heart_rate": 121,
        "timestamp": "2024-12-11T12:40:06.267"
    },
    {
        "heart_rate": 122,
        "timestamp": "2024-12-11T12:40:24"
    },
    {
        "heart_rate": 134,
        "timestamp": "2024-12-11T12:40:35.267"
    },
    {
        "heart_rate": 171,
        "timestamp": "2024-12-11T12:41:00"
    },
    {
        "heart_rate": 176,
        "timestamp": "2024-12-11T12:41:19.267"
    },
    {
        "heart_rate": 177,
        "timestamp": "2024-12-11T12:41:27"
    },
    {
        "heart_rate": 165,
        "timestamp": "2024-12-11T12:41:44.267"
    },
    {
        "heart_rate": 132,
        "timestamp": "2024-12-11T12:42:14"
    },
    {
        "heart_rate": 162,
        "timestamp": "2024-12-11T12:42:29.267"
    },
    {
        "heart_rate": 152,
        "timestamp": "2024-12-11T12:42:55"
    },
    {
        "heart_rate": 176,
        "timestamp": "2024-12-11T12:43:07.267"
    }
]